docx_json_converter/__init__.py
docx_json_converter/builder.py
docx_json_converter/cli.py
docx_json_converter/parser.py
docx_json_converter/prompts.py
docx_json_converter-0.1.0.dist-info/METADATA
docx_json_converter-0.1.0.dist-info/WHEEL
docx_json_converter-0.1.0.dist-info/entry_points.txt
docx_json_converter-0.1.0.dist-info/RECORD
