Metadata-Version: 2.4
Name: docx_json_converter
Version: 0.1.0
Summary: Convert .docx files to structured JSON and back.
Project-URL: Homepage, https://github.com/yourusername/docx_json_converter
Author-email: Your Name <you@example.com>
License: MIT
Requires-Python: >=3.8
Requires-Dist: python-docx>=1.0.0
